setup.py
ml/__init__.py
ml/dmlc/__init__.py
ml/dmlc/xgboost4j/__init__.py
ml/dmlc/xgboost4j/scala/__init__.py
ml/dmlc/xgboost4j/scala/spark/__init__.py
sparkxgb/__init__.py
sparkxgb/common.py
sparkxgb/util.py
sparkxgb/xgboost.py
sparkxgbX.egg-info/PKG-INFO
sparkxgbX.egg-info/SOURCES.txt
sparkxgbX.egg-info/dependency_links.txt
sparkxgbX.egg-info/not-zip-safe
sparkxgbX.egg-info/top_level.txt