Metadata-Version: 2.1
Name: sparkxgbX
Version: 0.1
Summary: a bugfix version for raw repo
Home-page: 
Author: unk
Author-email: unk@gmail.com
Classifier: Development Status :: 2 - Pre-Alpha
Classifier: Intended Audience :: Developers
Classifier: Programming Language :: Python :: 2.7
Classifier: Programming Language :: Python :: 3
Classifier: Programming Language :: Python :: 3.5
Classifier: Programming Language :: Python :: 3.6
Classifier: Programming Language :: Python :: 3.7
Requires-Python: >=2.7, <4
